vrt_lss_studio/__init__.py
vrt_lss_studio/api_client.py
vrt_lss_studio/api_response.py
vrt_lss_studio/configuration.py
vrt_lss_studio/exceptions.py
vrt_lss_studio/py.typed
vrt_lss_studio/rest.py
vrt_lss_studio/api/__init__.py
vrt_lss_studio/api/backups_api.py
vrt_lss_studio/api/custom_fields_api.py
vrt_lss_studio/api/custom_icons_api.py
vrt_lss_studio/api/experiments_api.py
vrt_lss_studio/api/explorer_api.py
vrt_lss_studio/api/external_routing_api.py
vrt_lss_studio/api/facts_api.py
vrt_lss_studio/api/hardlinks_api.py
vrt_lss_studio/api/locations_api.py
vrt_lss_studio/api/orders_api.py
vrt_lss_studio/api/performers_api.py
vrt_lss_studio/api/system_api.py
vrt_lss_studio/api/transports_api.py
vrt_lss_studio/api/trips_api.py
vrt_lss_studio/api/user_api.py
vrt_lss_studio/models/__init__.py
vrt_lss_studio/models/actualize_settings.py
vrt_lss_studio/models/assigned_performer.py
vrt_lss_studio/models/assigned_transport.py
vrt_lss_studio/models/attribute.py
vrt_lss_studio/models/basic_process.py
vrt_lss_studio/models/basic_state.py
vrt_lss_studio/models/box.py
vrt_lss_studio/models/box_compatibilities.py
vrt_lss_studio/models/box_limits.py
vrt_lss_studio/models/break_rules.py
vrt_lss_studio/models/calculation_history_element.py
vrt_lss_studio/models/calculation_info.py
vrt_lss_studio/models/calculation_settings.py
vrt_lss_studio/models/calculation_state.py
vrt_lss_studio/models/calculation_status.py
vrt_lss_studio/models/capacity.py
vrt_lss_studio/models/capacity_cost.py
vrt_lss_studio/models/capacity_limit.py
vrt_lss_studio/models/capacity_multiplier.py
vrt_lss_studio/models/capacity_statistics_load.py
vrt_lss_studio/models/capacity_statistics_ratio.py
vrt_lss_studio/models/capacity_statistics_sum.py
vrt_lss_studio/models/cargo.py
vrt_lss_studio/models/cargo_action.py
vrt_lss_studio/models/cargo_action_type.py
vrt_lss_studio/models/cargo_compatibilities.py
vrt_lss_studio/models/cargo_rotation_type.py
vrt_lss_studio/models/check_result.py
vrt_lss_studio-7.29.3120.dist-info/METADATA
vrt_lss_studio-7.29.3120.dist-info/WHEEL
vrt_lss_studio-7.29.3120.dist-info/top_level.txt
vrt_lss_studio-7.29.3120.dist-info/RECORD
